Metadata-Version: 2.1
Name: weather-forecast
Version: 0.47
Summary: Location based weather forecast package
Home-page: https://github.com/karthikziffer/weather_forecast
Author: Karthik
Author-email: karthik.cool1300@gmail.com
License: MIT
Platform: UNKNOWN
